flask_muck/__init__.py
flask_muck/callback.py
flask_muck/commands.py
flask_muck/exceptions.py
flask_muck/extension.py
flask_muck/open_api.py
flask_muck/py.typed
flask_muck/types.py
flask_muck/utils.py
flask_muck/views.py
flask_muck-0.4.2.dist-info/METADATA
flask_muck-0.4.2.dist-info/WHEEL
flask_muck-0.4.2.dist-info/licenses/LICENSE
flask_muck-0.4.2.dist-info/RECORD
