Metadata-Version: 2.4
Name: flask-muck
Version: 0.4.2
Summary: Batteries included framework for generating RESTful apis using Flask and SqlAlchemy.
Project-URL: Homepage, https://github.com/dtiesling/flask-muck
Project-URL: Repository, https://github.com/dtiesling/flask-muck
Project-URL: Documentation, https://dtiesling.github.io/flask-muck/
Author-email: Daniel Tiesling <tiesling@gmail.com>
License-File: LICENSE
Classifier: Framework :: Flask
Classifier: License :: OSI Approved :: MIT License
Classifier: Operating System :: OS Independent
Classifier: Programming Language :: Python :: 3
Requires-Python: >=3.9
Requires-Dist: apispec>=6.3.0
Requires-Dist: flasgger>=0.9.7.1
Requires-Dist: flask>=1.4.0
Requires-Dist: marshmallow-jsonschema-python3>=0.13.1
Requires-Dist: marshmallow>=3.15.0
Requires-Dist: pydantic>=2.0
Requires-Dist: pyhumps>=3.8.0
Requires-Dist: rich>=13.7.0
Requires-Dist: sqlalchemy>=1.4.0
Requires-Dist: webargs>=8.0.0
